{
  "moduleName": "Badge",
  "filePath": "src/lib/base/badge/Badge.svelte",
  "props": [
    {
      "name": "class",
      "kind": "let",
      "type": "string",
      "value": "''",
      "isFunction": false,
      "isFunctionDeclaration": false,
      "isRequired": false,
      "constant": false,
      "reactive": false
    },
    {
      "name": "element",
      "kind": "let",
      "type": "null | HTMLDivElement",
      "value": "null",
      "isFunction": false,
      "isFunctionDeclaration": false,
      "isRequired": false,
      "constant": false,
      "reactive": true
    },
    {
      "name": "value",
      "kind": "let",
      "isFunction": false,
      "isFunctionDeclaration": false,
      "isRequired": true,
      "constant": false,
      "reactive": false
    },
    {
      "name": "ceiling",
      "kind": "let",
      "isFunction": false,
      "isFunctionDeclaration": false,
      "isRequired": true,
      "constant": false,
      "reactive": false
    },
    {
      "name": "position",
      "kind": "let",
      "description": "position of the badge",
      "type": "{ x: 'left' | 'right' | 'center'; y: 'top' | 'bottom' | 'center' }",
      "value": "{     x: 'right',     y: 'top' }",
      "isFunction": false,
      "isFunctionDeclaration": false,
      "isRequired": false,
      "constant": false,
      "reactive": false
    }
  ],
  "moduleExports": [],
  "slots": [
    {
      "name": "__default__",
      "default": true,
      "fallback": "{value}",
      "slot_props": "{}"
    }
  ],
  "events": [],
  "typedefs": []
}
